pk_spectroscopy/__init__.py
pk_spectroscopy/_version.py
pk_spectroscopy/core.py
pk_spectroscopy/app/__init__.py
pk_spectroscopy/app/app.py
pk_spectroscopy/app/cli.py
pk_spectroscopy/app/samples/citric_acid.csv
pk_spectroscopy/app/samples/dry_red_wine_cationite.csv
pk_spectroscopy/app/samples/portwine_fraud_cationite.csv
pk_spectroscopy-0.1.2.dist-info/licenses/LICENSE
pk_spectroscopy-0.1.2.dist-info/METADATA
pk_spectroscopy-0.1.2.dist-info/WHEEL
pk_spectroscopy-0.1.2.dist-info/entry_points.txt
pk_spectroscopy-0.1.2.dist-info/top_level.txt
pk_spectroscopy-0.1.2.dist-info/RECORD
