Metadata-Version: 2.4
Name: pk_spectroscopy
Version: 0.1.2
Summary: Advanced analysis of objects with complex acid composition
Home-page: https://github.com/Sciencealone/pk_spectroscopy
Author: Mikhail Markovskii
Author-email: m.markovsky@gmail.com
License: MIT
Classifier: Programming Language :: Python :: 3
Classifier: License :: OSI Approved :: MIT License
Classifier: Topic :: Scientific/Engineering :: Chemistry
Classifier: Intended Audience :: Science/Research
Classifier: Operating System :: Microsoft :: Windows
Classifier: Operating System :: MacOS :: MacOS X
Classifier: Operating System :: POSIX :: Linux
Requires-Python: >=3.9
License-File: LICENSE
Requires-Dist: numpy==2.2.6
Requires-Dist: scipy==1.15.3
Requires-Dist: pandas==2.2.3
Requires-Dist: streamlit==1.45.1
Requires-Dist: plotly==6.1.1
Requires-Dist: plotly-express==0.4.1
Provides-Extra: dev
Requires-Dist: pytest; extra == "dev"
Requires-Dist: black; extra == "dev"
Requires-Dist: ruff; extra == "dev"
Requires-Dist: mypy; extra == "dev"
Requires-Dist: coverage; extra == "dev"
Dynamic: author
Dynamic: author-email
Dynamic: classifier
Dynamic: description
Dynamic: description-content-type
Dynamic: home-page
Dynamic: license
Dynamic: license-file
Dynamic: provides-extra
Dynamic: requires-dist
Dynamic: requires-python
Dynamic: summary
